lib_platform/__init__.py
lib_platform/__init__conf__.py
lib_platform/lib_platform.py
lib_platform/lib_platform_cli.py
lib_platform/py.typed
lib_platform-1.2.10.dist-info/LICENSE
lib_platform-1.2.10.dist-info/METADATA
lib_platform-1.2.10.dist-info/WHEEL
lib_platform-1.2.10.dist-info/entry_points.txt
lib_platform-1.2.10.dist-info/top_level.txt
lib_platform-1.2.10.dist-info/RECORD
